{
    "race": "Air Genasi",
    "fem-names": [
        "Aelara",
        "Zephyra",
        "Caelina",
        "Lyra",
        "Thalina",
        "Viora",
        "Elara",
        "Sylphie",
        "Amara",
        "Selenia",
        "Iridia",
        "Aria",
        "Selene",
        "Nereia",
        "Elowen",
        "Vespera",
        "Liora",
        "Calyra",
        "Elysia",
        "Faelina",
        "Vionna",
        "Celestia",
        "Myria",
        "Arwen",
        "Zinnia",
        "Aurelia",
        "Isolde",
        "Lysandra",
        "Evanthe",
        "Seraphina",
        "Anara",
        "Lyanna",
        "Kaelia",
        "Seren",
        "Melisande",
        "Vaila",
        "Nyssa",
        "Ione",
        "Talira",
        "Eirlys"
    ],
    "masc-names": [
        "Zephyr",
        "Caelum",
        "Aeron",
        "Thalos",
        "Orin",
        "Aric",
        "Sylas",
        "Elion",
        "Varian",
        "Jarek",
        "Lysander",
        "Kael",
        "Finian",
        "Talon",
        "Corin",
        "Varen",
        "Nyx",
        "Cedric",
        "Arion",
        "Kieran",
        "Galen",
        "Eryndor",
        "Jorin",
        "Dorian",
        "Lorian",
        "Alaric",
        "Rian",
        "Cael",
        "Valtor",
        "Orion",
        "Rowan",
        "Thorne",
        "Darian",
        "Fenwick",
        "Eldric",
        "Eamon",
        "Zephyrion",
        "Kaelan",
        "Draven",
        "Darian"
    ],
    "androgynous-names": [
        "Aelion",
        "Zephyris",
        "Caelith",
        "Sylian",
        "Elionis",
        "Veyra",
        "Ryne",
        "Elarae",
        "Arionis",
        "Taris",
        "Selion",
        "Vesperis",
        "Zephiris",
        "Elan",
        "Kestrel",
        "Seryn",
        "Ciri",
        "Vionis",
        "Aelith",
        "Thalorin",
        "Orius",
        "Lyren",
        "Sable",
        "Faelis",
        "Aziel",
        "Caelin",
        "Lorien",
        "Kiran",
        "Elyndor",
        "Nyxian",
        "Vaira",
        "Auron",
        "Selith",
        "Eryx",
        "Thalior",
        "Neris",
        "Kieranis",
        "Liora",
        "Aris",
        "Jorin"
    ],
    "surnames": [
        "Skyborn",
        "Windrider",
        "Cloudweaver",
        "Stormchaser",
        "Galeheart",
        "Starshadow",
        "Breezefury",
        "Moonblight",
        "Skybreaker",
        "Thunderstrike",
        "Horizoncall",
        "Frostwind",
        "Celestvale",
        "Zephyrveil",
        "Highwind",
        "Aetheris",
        "Cloudstrider",
        "Stormrider",
        "Starwhisper",
        "Tempestfall",
        "Skyflare",
        "Airborne",
        "Nightcloud",
        "Vortexcaller",
        "Celestcrest",
        "Wispwind",
        "Galeveil",
        "Stormsong",
        "Skyreach",
        "Moonshard",
        "Thunderpeak",
        "Starstorm",
        "Driftveil",
        "Skywatcher",
        "Cloudshaper",
        "Tempestwind",
        "Horizonshade",
        "Airstrider",
        "Frostveil",
        "Vortexwind"
    ],
    "ratio": {
        "feminine": 30,
        "masculine": 30,
        "androgynous": 30
    },
    "ageMin": 18,
    "ageMax": 120,
    "appearance": {
        "hair": {
            "type": [
                "Wavy",
                "Straight",
                "Curly",
                "Floating",
                "Translucent",
                "Feathery",
                "Streamlined",
                "Blown Back"
            ],
            "style": [
                "Flowing",
                "Tousled",
                "Tied Back",
                "Breezy",
                "Wispy",
                "Wind-Swept",
                "Cloud-Like",
                "Ethereal",
                "Gossamer",
                "Updo",
                "Braided"
            ],
            "color": [
                "Sky Blue",
                "Pale Grey",
                "Silver",
                "White",
                "Light Blue",
                "Translucent White",
                "Cloud White",
                "Azure",
                "Ice Blue",
                "Soft Platinum",
                "Pale Cyan",
                "Moonlit Silver",
                "Mist Grey",
                "Frosted Blue",
                "Icy Lavender",
                "Crystal Clear"
            ]
        },
        "eyes": [
            "Sky Blue",
            "Light Grey",
            "Silver",
            "White",
            "Crystal Clear",
            "Pale Azure",
            "Frosted Blue",
            "Translucent Blue",
            "Moonlight Silver",
            "Mist Grey",
            "Ice Blue",
            "Soft Platinum",
            "Glowing White",
            "Cloud Grey",
            "Ethereal Blue",
            "Celestial Grey",
            "Aurora Blue",
            "Glimmering Silver",
            "Pale Cyan",
            "Soft Lavender",
            "Opalescent White",
            "Sapphire Blue",
            "Frost Grey",
            "Airy Silver",
            "Hazy Blue"
        ],
        "height": [
            "Very Short",
            "Short",
            "Below Average Height",
            "Average Height",
            "Above Average Height",
            "Tall",
            "Very Tall"
        ],
        "build": [
            "Slender",
            "Athletic",
            "Muscular",
            "Sturdy",
            "Stocky",
            "Lanky",
            "Lean",
            "Bulky"
        ],
        "skin": {
            "color": [
                "Pale Blue",
                "Light Grey",
                "Cloud White",
                "Icy Blue",
                "Sky Blue",
                "Frost White",
                "Silver Mist",
                "Translucent Grey",
                "Moonlit White",
                "Celestial Blue",
                "Mist Blue",
                "Airy Grey",
                "Azure White",
                "Soft Blue",
                "Crystal Clear",
                "Pale Azure",
                "Light Silver",
                "Hazy Blue",
                "Ethereal White",
                "Glimmering Grey"
            ],
            "details": [
                "Subtle Veins",
                "Light Shimmer",
                "Faint Glow",
                "Cloud-like Patterns",
                "Icy Sparkles",
                "Mist-like Veil",
                "Moonlit Radiance",
                "Aurora-like Hues",
                "Glowing Mottles",
                "Soft Translucence",
                "Frosted Tips",
                "Airy Flickers",
                "Celestial Highlights",
                "Wind-swept Patterns",
                "Ethereal Glow",
                "Light Luminescence",
                "Soft Iridescence",
                "Sky Patterns",
                "Hazy Spots",
                "Glimmering Accents"
            ],
            "scar": [
                "Frosted Scars",
                "Mist-like Marks",
                "Light Hued Scars",
                "Veined Scars",
                "Ethereal Scar Patterns",
                "Cloudy Scars",
                "Translucent Scars",
                "Icy Burn Scars",
                "Air-formed Scars",
                "Celestial Scars",
                "Glowing Scars",
                "Soft Blue Scars",
                "Frost Markings",
                "Pale Blue Scarring",
                "Silver Scar Lines",
                "Ethereal Fade Scars",
                "Hazy Scars",
                "Light Mist Scars",
                "Frosted Patterns",
                "Subtle Blue Scars"
            ],
            "birthmark": [
                "Cloud-like Birthmark",
                "Mist-shaped Mark",
                "Sky Blue Spot",
                "Icy Birthmark",
                "Ethereal Patch",
                "Celestial Birthmark",
                "Frosted Spot",
                "Light Blue Mark",
                "Shimmering Birthmark",
                "Airy Spot",
                "Glowing Birthmark",
                "Soft Grey Mark",
                "Ethereal Veil Birthmark",
                "Pale Blue Patch",
                "Frost-like Mark",
                "Hazy Birthmark",
                "Moonlit Spot",
                "Soft Iridescent Mark",
                "Celestial Patch",
                "Glimmering Birthmark"
            ],
            "tattoos": [
                "Cloud Patterns",
                "Sky Symbols",
                "Icy Runes",
                "Celestial Marks",
                "Ethereal Designs",
                "Mist Tattoos",
                "Frosted Art",
                "Air-themed Tattoos",
                "Glowing Patterns",
                "Light Blue Ink",
                "Glimmering Symbols",
                "Frost-like Designs",
                "Soft Blue Etchings",
                "Moonlit Tattoos",
                "Celestial Lines",
                "Aurora-themed Tattoos",
                "Ethereal Script",
                "Subtle Cloud Inks",
                "Airy Patterns",
                "Sky-themed Art"
            ],
            "bodyPart": [
                "Face",
                "Neck",
                "Shoulder",
                "Back",
                "Chest",
                "Arm",
                "Forearm",
                "Hand",
                "Leg",
                "Thigh",
                "Calf",
                "Foot"
            ]
        }
    }
}