{
    "fem-names": [
        "Baggi",
        "Emen",
        "Engong",
        "Kansif",
        "Myev",
        "Neega",
        "Ovak",
        "Ownka",
        "Shautha",
        "Sutha",
        "Vola",
        "Volen",
        "Yevelda",
        "Brakka",
        "Gruva",
        "Hagna",
        "Korra",
        "Lakra",
        "Morga",
        "Nagra",
        "Orga",
        "Pesha",
        "Ragga",
        "Senga",
        "Targa",
        "Urka",
        "Vakka",
        "Wenna",
        "Zagga",
        "Zorna",
        "Asha",
        "Grima",
        "Hilda",
        "Iona",
        "Kara",
        "Leena",
        "Mara",
        "Nessa",
        "Osha",
        "Pella",
        "Rita",
        "Sasha",
        "Tessa",
        "Una",
        "Vera",
        "Willa",
        "Yara",
        "Zara"
    ],
    "masc-names": [
        "Dench",
        "Feng",
        "Gell",
        "Henk",
        "Holg",
        "Imsh",
        "Keth",
        "Krusk",
        "Mhurren",
        "Ront",
        "Shump",
        "Thokk",
        "Brog",
        "Druk",
        "Gor",
        "Hok",
        "Jok",
        "Krog",
        "Lorg",
        "Mok",
        "Nok",
        "Ogg",
        "Porg",
        "Rug",
        "Snog",
        "Tog",
        "Ugg",
        "Vok",
        "Wog",
        "Zog",
        "Agar",
        "Bruk",
        "Dorg",
        "Erok",
        "Frok",
        "Grok",
        "Horg",
        "Irok",
        "Jorg",
        "Krak",
        "Lok",
        "Morg",
        "Narg",
        "Ork",
        "Prak",
        "Quok",
        "Rak",
        "Sorg",
        "Tark"
    ],
    "androgynous-names": [
        "Dak",
        "Vor",
        "Rog",
        "Zag",
        "Truk",
        "Mog",
        "Raz",
        "Lok",
        "Tug",
        "Gor",
        "Nor",
        "Yar",
        "Arda",
        "Bryn",
        "Caro",
        "Dara",
        "Elan",
        "Finn",
        "Gale",
        "Hale",
        "Joss",
        "Keir",
        "Lior",
        "Mara",
        "Nico",
        "Orin",
        "Paz",
        "Quin",
        "Rian",
        "Shay",
        "Tavi",
        "Umi",
        "Vale",
        "Wren",
        "Xan",
        "Yin",
        "Zan",
        "Ari",
        "Blair",
        "Casey",
        "Drew",
        "Eli",
        "Fenn",
        "Gray",
        "Harper",
        "Indy",
        "Jules",
        "Kit",
        "Lane",
        "Marlow"
    ],
    "surnames": [
        "Bloodfist",
        "Stonecrusher",
        "Ironskull",
        "Bonebreaker",
        "Darkaxe",
        "Steelmaw",
        "Grimblade",
        "Thunderfury",
        "Stormrage",
        "Skullsplitter",
        "Frostfang",
        "Rageclaw",
        "Blightbane",
        "Doomhammer",
        "Flameheart",
        "Shadowhunter",
        "Ironhide",
        "Deathbringer",
        "Warcry",
        "Earthshaker",
        "Bloodaxe",
        "Stormbringer",
        "Ironfist",
        "Darkblade",
        "Blacktooth",
        "Stonefury",
        "Grimjaw",
        "Thunderstrike",
        "Wargrin",
        "Frosthammer",
        "Rageblade",
        "Blightfang",
        "Doomclaw",
        "Flamefury",
        "Shadowstrike",
        "Ironjaw",
        "Deathclaw",
        "Warblade",
        "Earthstrike",
        "Bloodclaw",
        "Stormfang",
        "Ironskull",
        "Darkfang",
        "Blackclaw",
        "Stoneclaw",
        "Grimclaw",
        "Thunderclaw",
        "Warclaw",
        "Frostclaw",
        "Rageclaw"
    ],
    "ratio": {
        "feminine": 40,
        "masculine": 40,
        "androgynous": 20
    },
    "ageMin": 14,
    "ageMax": 75,
    "appearance": {
        "facialHair": [
            "Clean-shaven",
            "Stubble",
            "Goatee",
            "Moustache",
            "Full Beard",
            "Chinstrap",
            "Sideburns",
            "Braided Beard",
            "Forked Beard",
            "Soul Patch"
        ],
        "hair": {
            "type": [
                "Straight",
                "Wavy",
                "Curly",
                "Coarse",
                "Bald"
            ],
            "style": [
                "Short and Cropped",
                "Medium Length",
                "Long and Flowing",
                "Ponytail",
                "Braided",
                "Shaggy",
                "Topknot",
                "Mohawk",
                "Dreadlocks",
                "Shaved Sides",
                "Loose and Wild"
            ],
            "color": [
                "Black",
                "Dark Gray",
                "Steel Gray",
                "Light Gray",
                "Charcoal",
                "Salt and Pepper",
                "White"
            ]
        },
        "eyes": [
            "Brown",
            "Hazel",
            "Amber",
            "Green",
            "Blue",
            "Gray",
            "Dark brown",
            "Light brown",
            "Golden",
            "Violet",
            "Deep blue",
            "Ice blue",
            "Dark green",
            "Light green",
            "Black"
        ],
        "height": [
            "Very Short",
            "Short",
            "Below Average Height",
            "Average Height",
            "Above Average Height",
            "Tall",
            "Very Tall"
        ],
        "build": [
            "Athletic",
            "Muscular",
            "Sturdy",
            "Stocky",
            "Lean",
            "Bulky"
        ],
        "skin": {
            "color": [
                "Pale Gray",
                "Light Gray",
                "Medium Gray",
                "Dark Gray",
                "Ashen Gray",
                "Stone Gray",
                "Pale Green",
                "Light Green",
                "Medium Green",
                "Dark Green",
                "Olive Green",
                "Forest Green",
                "Moss Green",
                "Swamp Green",
                "Sage Green",
                "Muted Green",
                "Bluish Gray",
                "Yellowish Green",
                "Grayish Green",
                "Dusky Green"
            ],
            "details": [
                "Freckles",
                "Moles",
                "Age spots",
                "Wrinkles",
                "Dimples",
                "Smooth",
                "Rough",
                "Oily",
                "Dry",
                "Scarred",
                "Sunburned",
                "Tanned",
                "Birthmarks"
            ],
            "scar": [
                "Jagged scar",
                "Slash mark",
                "Burn mark",
                "Puncture wound",
                "Claw mark",
                "Battle wound",
                "Tribal scarification",
                "Whip mark",
                "Talon scratch",
                "Healed gash"
            ],
            "birthmark": [
                "Irregular shape",
                "Dark patch",
                "Light patch",
                "Freckle-like cluster",
                "Streak-like mark",
                "Patchy discoloration",
                "Spots",
                "Mottled pattern",
                "Blotchy mark",
                "Rugged shape"
            ],
            "tattoos": [
                "Warrior emblem",
                "Clan symbol",
                "Beast totem",
                "Battle scene",
                "Skull and bones",
                "War paint pattern",
                "Orcish script",
                "Totem animal",
                "Weapon motif",
                "Thunderbolt",
                "Battle axe",
                "Orcish rune",
                "Dragon",
                "Phoenix",
                "Spiked club",
                "Barbed wire",
                "Flames",
                "Wolf",
                "Bear"
            ],
            "bodyPart": [
                "Face",
                "Neck",
                "Shoulder",
                "Back",
                "Chest",
                "Arm",
                "Forearm",
                "Hand",
                "Leg",
                "Thigh",
                "Calf",
                "Foot"
            ]
        }
    }
}